LICENSE
MANIFEST.in
README.md
setup.py
restcli/__init__.py
restcli/cliparser.py
restcli/config.py
restcli/options.py
restcli/profile.py
restcli/request.py
restcli/restcli.conf
restcli/restcli.py
restcli.egg-info/PKG-INFO
restcli.egg-info/SOURCES.txt
restcli.egg-info/dependency_links.txt
restcli.egg-info/entry_points.txt
restcli.egg-info/requires.txt
restcli.egg-info/top_level.txt