Metadata-Version: 1.0
Name: restcli
Version: 0.1
Summary: Command line REST request tool
Home-page: https://github.com/jykntr/rest-cli-client
Author: jykntr
Author-email: jykntr@gmail.com
License: MIT
Keywords: rest http
Platform: UNKNOWN
